simager/__init__.py
simager/data/__init__.py
simager/data/normalizer.p
simager/data/stop_w.p
simager/example/__init__.py
simager/ml/__init__.py
simager/ml/_bayes_params.py
simager/ml/_grid_params.py
simager/ml/_mlconfig.py
simager/ml/_model.py
simager/ml/_modelops.py
simager/ml/_pipelines.py
simager/preprocess/__init__.py
simager/preprocess/_preprocess.py
simager-0.1.2.dist-info/LICENSE
simager-0.1.2.dist-info/METADATA
simager-0.1.2.dist-info/WHEEL
simager-0.1.2.dist-info/top_level.txt
simager-0.1.2.dist-info/RECORD
