Metadata-Version: 2.1
Name: simager
Version: 0.1.2
Summary: Simple tools for auto classification and text preprocessing
Home-page: https://pypi.org/project/simager
Author: ulwan
Author-email: ulwan.nashihun@gmail.com
License: MIT
Keywords: nlp,text-processing,machine-learning,data-scientist,text-cleaner
Classifier: Programming Language :: Python :: 3
Classifier: License :: OSI Approved :: MIT License
Classifier: Operating System :: OS Independent
Classifier: Intended Audience :: Developers
Classifier: Topic :: Software Development :: Build Tools
Classifier: Topic :: Scientific/Engineering :: Artificial Intelligence
Classifier: Topic :: Text Processing
Requires-Python: >=3.6
License-File: LICENSE
Requires-Dist: emoji (==0.6.0)
Requires-Dist: beautifulsoup4 (==4.9.3)
Requires-Dist: scikit-learn (==0.24.2)
Requires-Dist: imbalanced-learn (==0.8.1)
Requires-Dist: lightgbm (==3.3.1)
Requires-Dist: xgboost (==1.5.0)
Requires-Dist: catboost (==1.0.3)
Requires-Dist: matplotlib (==3.3.4)
Requires-Dist: pandas (==1.1.5)
Requires-Dist: scikit-optimize (==0.9.0)
Requires-Dist: scipy (==1.5.4)
